flamesFinder/__init__.py
flamesFinder/flames.py
flamesFinder-0.1.2.dist-info/LICENSE
flamesFinder-0.1.2.dist-info/METADATA
flamesFinder-0.1.2.dist-info/WHEEL
flamesFinder-0.1.2.dist-info/top_level.txt
flamesFinder-0.1.2.dist-info/RECORD
